fifo.v
module fifo
   #(
      parameter DATA_WIDTH = 16,
      parameter LOG2_DEPTH = 4 // i.e. fifo depth=2**LOG2_DEPTH
   )
   (
      input [DATA_WIDTH-1:0]  din,
      input wr_en,
      input rd_en,
      output [DATA_WIDTH-1:0] dout,
      output full,
      output empty,
      input clk,
      input reset
   );
 
   parameter MAX_COUNT = 2**LOG2_DEPTH;
   reg   [LOG2_DEPTH-1 : 0]   rd_ptr;
   reg   [LOG2_DEPTH-1 : 0]   wr_ptr;
   reg   [DATA_WIDTH-1 : 0]   mem[MAX_COUNT-1 : 0];   //memory size: 2**LOG2_DEPTH
   reg   [LOG2_DEPTH : 0]     depth_cnt;
 
   always @(posedge clk) begin
      if(reset) begin
         wr_ptr <= 'h0;
         rd_ptr <= 'h0;
      end // end if
      else begin
         if(wr_en)begin
            wr_ptr <= wr_ptr+1;
         end
         if(rd_en)
            rd_ptr <= rd_ptr+1;
      end //end else
   end//end always
 
   assign empty= (depth_cnt=='h0);
   assign full = (depth_cnt==MAX_COUNT);
 
   //comment if you want a registered dout
   assign dout = rd_en ? mem[rd_ptr]:'h0;
 
   always @(posedge clk) begin
      if (wr_en)
         mem[wr_ptr] <= din;
   end //end always
 
 
   always @(posedge clk) begin
      if (reset)
         depth_cnt <= 'h0;
      else begin
         case({rd_en,wr_en})
            2'b10    :  depth_cnt <= depth_cnt-1;
            2'b01    :  depth_cnt <= depth_cnt+1;
         endcase
      end //end else
   end //end always
 
endmodule

tfifo_full.v
module test_fifo;

reg reset, clk, wr_en, rd_en;
wire empty, full;
reg [15:0]din;
wire [15:0] dout;

//устанавливаем экземпляр тестируемого модуля
fifo fifo_inst(din, wr_en, rd_en, dout, full, empty, clk, reset);

//моделируем сигнал тактовой частоты
always
  #4 clk = ~clk;

//от начала времени...

initial
begin
  clk = 0;
  reset = 0;
  din = 16'h00;
  wr_en = 1'b0;
  rd_en = 1'b0;

//через временной интервал "40" подаем сигнал сброса
  #40 reset = 1; 

//еще через время "6" снимаем сигнал сброса

  #6 reset = 0;

//пауза длительностью "30"
  #4; 

//ждем фронта тактовой частоты и сразу после нее подаем сигнал записи
  @(posedge clk) 
  #0
    begin
      din = 16'h1;
      wr_en = 1'b1;
    end


//по следующему фронту записываем в регистр, после окончания записи читаем
  @(posedge clk)
  #8
    begin
      din=16'h17;
      #8
      din=16'h18;
      #8
      din=16'h19;
      #8
      din=16'h20;
      #8
      din=16'h21;
      #8
      din=16'h22;
      #8
      din=16'h23;
      #8
      din=16'h24;
      #8
      din=16'h25;
      #8
      din=16'h26;
      #8
      din=16'h27;
      #8
      din=16'h28;
      #8
      din=16'h29;
      #8
      din=16'h30;
      #8
      din=16'h31;
      #8
      din=16'h32;
      #8
      din=16'h33;
      #8
      din=16'h34;
      #8
      din=16'h35;
      #8
      din=16'h36;
      #8
      din=16'h37;
      #8
      din=16'h38;
      #8
      din=16'h39;
      #8
      wr_en=1'b0;
      rd_en = 1'b1;
      #25
      rd_en = 1'b0;
    end

end

//заканчиваем симуляцию в момент времени "300"
initial
begin
  #300 $finish;
end

//создаем файл VCD для последующего анализа сигналов
initial
begin
  $dumpfile("out_fifo.vcd");
  $dumpvars(0,test_fifo);
end

//наблюдаем на некоторыми сигналами системы
initial 
$monitor($stime,, reset,, clk,,, din,, wr_en,, rd_en,, dout,, empty,, full); 

endmodule

out_fifo.vcd
$date
	Mon Oct 01 11:33:13 2018
$end
$version
	Icarus Verilog
$end
$timescale
	1s
$end
$scope module test_fifo $end
$var wire 16 ! dout [15:0] $end
$var wire 1 " empty $end
$var wire 1 # full $end
$var reg 1 $ clk $end
$var reg 16 % din [15:0] $end
$var reg 1 & rd_en $end
$var reg 1 ' reset $end
$var reg 1 ( wr_en $end
$scope module fifo_inst $end
$var wire 1 ) clk $end
$var wire 16 * din [15:0] $end
$var wire 16 + dout [15:0] $end
$var wire 1 " empty $end
$var wire 1 # full $end
$var wire 1 , rd_en $end
$var wire 1 - reset $end
$var wire 1 . wr_en $end
$var reg 5 / depth_cnt [4:0] $end
$var reg 4 0 rd_ptr [3:0] $end
$var reg 4 1 wr_ptr [3:0] $end
$upscope $end
$upscope $end
$enddefinitions $end
#0
$dumpvars
bx 1
bx 0
bx /
0.
0-
0,
b0 +
b0 *
0)
0(
0'
0&
b0 %
0$
x#
x"
b0 !
$end
#4
1$
1)
#8
0$
0)
#12
1$
1)
#16
0$
0)
#20
1$
1)
#24
0$
0)
#28
1$
1)
#32
0$
0)
#36
1$
1)
#40
0$
0)
1'
1-
#44
b0 /
1"
0#
b0 0
b0 1
1$
1)
#46
0'
0-
#48
0$
0)
#52
1(
1.
b1 %
b1 *
1$
1)
#56
0$
0)
#60
b1 /
0"
b1 1
1$
1)
#64
0$
0)
#68
b10 1
b10 /
1$
1)
b10111 %
b10111 *
#72
0$
0)
#76
b11 /
b11 1
1$
1)
b11000 %
b11000 *
#80
0$
0)
#84
b100 1
b100 /
1$
1)
b11001 %
b11001 *
#88
0$
0)
#92
b101 /
b101 1
1$
1)
b100000 %
b100000 *
#96
0$
0)
#100
b110 1
b110 /
1$
1)
b100001 %
b100001 *
#104
0$
0)
#108
b111 /
b111 1
1$
1)
b100010 %
b100010 *
#112
0$
0)
#116
b1000 1
b1000 /
1$
1)
b100011 %
b100011 *
#120
0$
0)
#124
b1001 /
b1001 1
1$
1)
b100100 %
b100100 *
#128
0$
0)
#132
b1010 1
b1010 /
1$
1)
b100101 %
b100101 *
#136
0$
0)
#140
b1011 /
b1011 1
1$
1)
b100110 %
b100110 *
#144
0$
0)
#148
b1100 1
b1100 /
1$
1)
b100111 %
b100111 *
#152
0$
0)
#156
b1101 /
b1101 1
1$
1)
b101000 %
b101000 *
#160
0$
0)
#164
b1110 1
b1110 /
1$
1)
b101001 %
b101001 *
#168
0$
0)
#172
b1111 /
b1111 1
1$
1)
b110000 %
b110000 *
#176
0$
0)
#180
b0 1
b10000 /
1#
1$
1)
b110001 %
b110001 *
#184
0$
0)
#188
b10001 /
0#
b1 1
1$
1)
b110010 %
b110010 *
#192
0$
0)
#196
b10 1
b10010 /
1$
1)
b110011 %
b110011 *
#200
0$
0)
#204
b10011 /
b11 1
1$
1)
b110100 %
b110100 *
#208
0$
0)
#212
b100 1
b10100 /
1$
1)
b110101 %
b110101 *
#216
0$
0)
#220
b10101 /
b101 1
1$
1)
b110110 %
b110110 *
#224
0$
0)
#228
b110 1
b10110 /
1$
1)
b110111 %
b110111 *
#232
0$
0)
#236
b10111 /
b111 1
1$
1)
b111000 %
b111000 *
#240
0$
0)
#244
b1000 1
b11000 /
1$
1)
b111001 %
b111001 *
#248
0$
0)
#252
b10111 /
b1 0
b110011 !
b110011 +
1$
1)
1&
1,
0(
0.
#256
0$
0)
#260
b110100 !
b110100 +
b10 0
b10110 /
1$
1)
#264
0$
0)
#268
b110101 !
b110101 +
b10101 /
b11 0
1$
1)
#272
0$
0)
#276
b110110 !
b110110 +
b100 0
b10100 /
1$
1)
#277
b0 !
b0 +
0&
0,
