fifo.v
module fifo
   #(
      parameter DATA_WIDTH = 16,
      parameter LOG2_DEPTH = 4 // i.e. fifo depth=2**LOG2_DEPTH
   )
   (
      input [DATA_WIDTH-1:0]  din,
      input wr_en,
      input rd_en,
      output [DATA_WIDTH-1:0] dout,
      output full,
      output empty,
      input clk,
      input reset
   );
 
   parameter MAX_COUNT = 2**LOG2_DEPTH;
   reg   [LOG2_DEPTH-1 : 0]   rd_ptr;
   reg   [LOG2_DEPTH-1 : 0]   wr_ptr;
   reg   [DATA_WIDTH-1 : 0]   mem[MAX_COUNT-1 : 0];   //memory size: 2**LOG2_DEPTH
   reg   [LOG2_DEPTH : 0]     depth_cnt;
 
   always @(posedge clk) begin
      if(reset) begin
         wr_ptr <= 'h0;
         rd_ptr <= 'h0;
      end // end if
      else begin
         if(wr_en)begin
            wr_ptr <= wr_ptr+1;
         end
         if(rd_en)
            rd_ptr <= rd_ptr+1;
      end //end else
   end//end always
 
   assign empty= (depth_cnt=='h0);
   assign full = (depth_cnt==MAX_COUNT);
 
   //comment if you want a registered dout
   assign dout = rd_en ? mem[rd_ptr]:'h0;
 
   always @(posedge clk) begin
      if (wr_en)
         mem[wr_ptr] <= din;
   end //end always
 
 
   always @(posedge clk) begin
      if (reset)
         depth_cnt <= 'h0;
      else begin
         case({rd_en,wr_en})
            2'b10    :  depth_cnt <= depth_cnt-1;
            2'b01    :  depth_cnt <= depth_cnt+1;
         endcase
      end //end else
   end //end always
 
endmodule

tfifo.v
module test_fifo;

reg reset, clk, wr_en, rd_en;
wire empty, full;
reg [15:0]din;
wire [15:0] dout;

//устанавливаем экземпляр тестируемого модуля
fifo fifo_inst(din, wr_en, rd_en, dout, full, empty, clk, reset);

//моделируем сигнал тактовой частоты
always
  #10 clk = ~clk;

//от начала времени...

initial
begin
  clk = 0;
  reset = 0;
  din = 16'h00;
  wr_en = 1'b0;
  rd_en = 1'b0;

//через временной интервал "40" подаем сигнал сброса
  #40 reset = 1; 

//еще через время "4" снимаем сигнал сброса

  #14 reset = 0;

//пауза длительностью "30"
  #30; 

//ждем фронта тактовой частоты и сразу после нее подаем сигнал записи
  @(posedge clk) 
  #0
    begin
      din = 16'h55;
      wr_en = 1'b1;
    end

//ждем фронта тактовой частоты и сразу после нее подаем сигнал чтения
  @(posedge clk) 
  #10
    begin
      rd_en = 1'b1;
    end

//по следующему фронту снимаем сигнал записи и чтения
  @(posedge clk)
  #10
    begin
      wr_en = 1'b0;
      din=16'h17;
      rd_en = 1'b0;
    end

end 

//заканчиваем симуляцию в момент времени "300"
initial
begin
  #300 $finish;
end

//создаем файл VCD для последующего анализа сигналов
initial
begin
  $dumpfile("out_fifo.vcd");
  $dumpvars(0,test_fifo);
end

//наблюдаем на некоторыми сигналами системы
initial 
$monitor($stime,, reset,, clk,,, din,, wr_en,, rd_en,, dout,, empty,, full); 

endmodule

out_fifo.vcd
$date
	Sun Sep 30 18:26:30 2018
$end
$version
	Icarus Verilog
$end
$timescale
	1s
$end
$scope module test_fifo $end
$var wire 16 ! dout [15:0] $end
$var wire 1 " empty $end
$var wire 1 # full $end
$var reg 1 $ clk $end
$var reg 16 % din [15:0] $end
$var reg 1 & rd_en $end
$var reg 1 ' reset $end
$var reg 1 ( wr_en $end
$scope module fifo_inst $end
$var wire 1 ) clk $end
$var wire 16 * din [15:0] $end
$var wire 16 + dout [15:0] $end
$var wire 1 " empty $end
$var wire 1 # full $end
$var wire 1 , rd_en $end
$var wire 1 - reset $end
$var wire 1 . wr_en $end
$var reg 5 / depth_cnt [4:0] $end
$var reg 4 0 rd_ptr [3:0] $end
$var reg 4 1 wr_ptr [3:0] $end
$upscope $end
$upscope $end
$enddefinitions $end
#0
$dumpvars
bx 1
bx 0
bx /
0.
0-
0,
b0 +
b0 *
0)
0(
0'
0&
b0 %
0$
x#
x"
b0 !
$end
#10
1$
1)
#20
0$
0)
#30
1$
1)
#40
0$
0)
1'
1-
#50
b0 0
b0 1
b0 /
1"
0#
1$
1)
#54
0'
0-
#60
0$
0)
#70
1$
1)
#80
0$
0)
#90
1(
1.
b1010101 %
b1010101 *
1$
1)
#100
0$
0)
#110
b1 /
0"
b1 1
1$
1)
#120
b1010101 !
b1010101 +
1&
1,
0$
0)
#130
b1 0
b10 1
1$
1)
#140
b0 !
b0 +
0&
0,
b10111 %
b10111 *
0(
0.
0$
0)
